{
  "app": {
    "signingConfigs": [
      {
        "name": "release",
        "type": "HarmonyOS",
        "material": {
          "storeFile": "D:/HarmonyOS/my_secrets-master/quickysticker_sign.p12",
          "storePassword": "0000001D8AFD168633A99FF1F7866E7B3F96E9806A2596B14F7B3FBAB3F0C89F1B6B61C92B912EE49A3F61FA1C",
          "keyAlias": "QuickySticker",
          "keyPassword": "0000001D17EB93E6375468C6200E65F06CBAA7F26E9B42375905D8637287A4272B3FBDA14BE646937DA8722E40",
          "signAlg": "SHA256withECDSA",
          "profile": "D:/HarmonyOS/my_secrets-master/cloudpureplay_releaseRelease.p7b",
          "certpath": "D:/HarmonyOS/my_secrets-master/quickysticker.cer"
        }
      },
      {
        "name": "debug",
        "type": "HarmonyOS",
        "material": {
          "storeFile": "D:/HarmonyOS/my_secrets-master/quickysticker_sign.p12",
          "storePassword": "0000001D8AFD168633A99FF1F7866E7B3F96E9806A2596B14F7B3FBAB3F0C89F1B6B61C92B912EE49A3F61FA1C",
          "keyAlias": "QuickySticker",
          "keyPassword": "0000001D17EB93E6375468C6200E65F06CBAA7F26E9B42375905D8637287A4272B3FBDA14BE646937DA8722E40",
          "signAlg": "SHA256withECDSA",
          "profile": "D:/HarmonyOS/my_secrets-master/cloudpureplay_debugDebug.p7b",
          "certpath": "D:/HarmonyOS/my_secrets-master/debug_quickstickr.cer"
        }
      }
    ],
    "products": [
      {
        "name": "default",
        "signingConfig": "release",
        "targetSdkVersion": "6.0.0(20)",
        "compatibleSdkVersion": "5.1.0(18)",
        "runtimeOS": "HarmonyOS",
        "buildOption": {
          "strictMode": {
            "caseSensitiveCheck": true,
            "useNormalizedOHMUrl": true
          }
        }
      }
    ],
    "buildModeSet": [
      {
        "name": "debug",
      },
      {
        "name": "release"
      }
    ]
  },
  "modules": [
    {
      "name": "default",
      "srcPath": "./product/default",
      "targets": [
        {
          "name": "default",
          "applyToProducts": [
            "default"
          ]
        }
      ]
    },
    {
      "name": "base",
      "srcPath": "./common/base",
    },
    {
      "name": "player_ui",
      "srcPath": "./feature/player_ui"
    },
    {
      "name": "ui_components",
      "srcPath": "./common/ui_components",
    },
    {
      "name": "cloud_api",
      "srcPath": "./apis/cloud_api"
    },
    {
      "name": "app_settings",
      "srcPath": "./feature/app_settings",
    },
    {
      "name": "explore",
      "srcPath": "./feature/explore",
    },
    {
      "name": "common_resources",
      "srcPath": "./common/common_resources",
    },
    {
      "name": "api_adapter",
      "srcPath": "./apis/api_adapter",
    },
    {
      "name": "music_library",
      "srcPath": "./feature/music_library",
    },
    {
      "name": "navidrome_api",
      "srcPath": "./apis/navidrome_api",
      "targets": [
        {
          "name": "default",
          "applyToProducts": [
            "default"
          ]
        }
      ]
    },
    {
      "name": "wearable",
      "srcPath": "./product/wearable",
      "targets": [
        {
          "name": "default",
          "applyToProducts": [
            "default"
          ]
        }
      ]
    },
    {
      "name": "wearable_player_ui",
      "srcPath": "./feature/wearable/wearable_player_ui",
    },
    {
      "name": "wearable_music_library",
      "srcPath": "./feature/wearable/wearable_music_library",
    },
    {
      "name": "wearable_settings",
      "srcPath": "./feature/wearable/wearable_settings",
    },
    {
      "name": "wearable_ui_components",
      "srcPath": "./common/wearable_ui_components",
    }
  ]
}